pyrost/__init__.py
pyrost/abberations_fit.py
pyrost/data_container.py
pyrost/data_processing.py
pyrost/protocol.py
pyrost/bin/__init__.py
pyrost/bin/beam_calc.c
pyrost/bin/beam_calc.cpython-37m-darwin.so
pyrost/bin/beam_calc.pxd
pyrost/bin/beam_calc.pyx
pyrost/bin/st_utils.c
pyrost/bin/st_utils.cpython-37m-darwin.so
pyrost/bin/st_utils.pyx
pyrost/config/cxi_protocol.ini
pyrost/config/parameters.ini
pyrost/simulation/__init__.py
pyrost/simulation/__main__.py
pyrost/simulation/st_sim.py
pyrost/simulation/st_sim_param.py
pyrost-0.1.9.dist-info/LICENSE
pyrost-0.1.9.dist-info/METADATA
pyrost-0.1.9.dist-info/WHEEL
pyrost-0.1.9.dist-info/top_level.txt
pyrost-0.1.9.dist-info/RECORD
