Metadata-Version: 2.1
Name: pyrost
Version: 0.1.9
Summary: UNKNOWN
Home-page: https://github.com/simply-nicky/rst
Author: Nikolay Ivanov
Author-email: nikolay.ivanov@desy.de
License: UNKNOWN
Platform: UNKNOWN
Classifier: Programming Language :: Python
Classifier: License :: OSI Approved :: GNU General Public License v3 (GPLv3)
Classifier: Operating System :: OS Independent
Requires-Python: >=3.6
Requires-Dist: Cython
Requires-Dist: CythonGSL
Requires-Dist: h5py
Requires-Dist: numpy
Requires-Dist: scipy
Provides-Extra: interactive
Requires-Dist: matplotlib ; extra == 'interactive'
Requires-Dist: jupyter ; extra == 'interactive'
Requires-Dist: pyximport ; extra == 'interactive'
